{
  "231218": {
    "text": "Profile Mood Video<br>NOMAD DOY (노매드 도의)<br><br>📽 https://youtu.be/qqw-lAOiRrE<br><br>#NOMAD #노매드<br>#DOY #SANGHA #ONE #RIVR #JUNHO<br>#도의 #상하 #원 #리버 #준호"
  },
  "231227": {
    "text": "노매드, 1st EP 수록곡 ‘Lights on’ 퍼포먼스 비디오 오늘 선공개<br><br>NOMAD will pre-release performance video of 'Lights on' that B-side Track of 1st EP today<br><br>http://naver.me/GzgRxcGt<br><br>#NOMAD #노매드<br>#DOY #SANGHA #ONE #RIVR #JUNHO<br>#도의 #상하 #원 #리버 #준호"
  },
  "231228": {
    "text": "📷 Behind cut #도의<br><br>NOMAD 노매드 'Lights on' Performance Video<br><br>🎬https://youtu.be/SPh6FzSjOVk<br><br>#NOMAD #노매드<br>#DOY #SANGHA #ONE #RIVR #JUNHO<br>#도의 #상하 #원 #리버 #준호"
  },
  "231230": {
    "text": "📷 Behind cut #노매드<br><br>NOMAD 노매드 'Lights on' Performance Video<br><br>🎬https://youtu.be/SPh6FzSjOVk<br><br>#NOMAD #노매드<br>#DOY #SANGHA #ONE #RIVR #JUNHO<br>#도의 #상하 #원 #리버 #준호<br><br>Behind cut #노매드<br><br>NOMAD 노매드 'Lights on' Performance Video<br><br>🎬https://youtu.be/SPh6FzSjOVk<br><br>#NOMAD #노매드<br>#DOY #SANGHA #ONE #RIVR #JUNHO<br>#도의 #상하 #원 #리버 #준호"
  },
  "240101": {
    "text": "📷 Behind cut #노매드<br><br>NOMAD 노매드 'Lights on' Performance Video<br><br>🎬https://youtu.be/SPh6FzSjOVk<br><br>#NOMAD #노매드<br>#DOY #SANGHA #ONE #RIVR #JUNHO<br>#도의 #상하 #원 #리버 #준호<br><br>Behind cut #노매드<br><br>NOMAD 노매드 'Lights on' Performance Video<br><br>🎬https://youtu.be/SPh6FzSjOVk<br><br>#NOMAD #노매드<br>#DOY #SANGHA #ONE #RIVR #JUNHO<br>#도의 #상하 #원 #리버 #준호"
  },
  "240112": {
    "text": "글로벌 유명 프로듀서 대거 참여...‘노매드’ 1st EP 수록곡 추가공개<br><br>Many famous global producers participate... Additional songs included in 'NOMAD' 1st EP released<br><br>https://mhns.co.kr/news/articleView.html?idxno=571311<br><br>#NOMAD #노매드 #DOY #SANGHA #ONE #RIVR #JUNHO #도의 #상하 #원 #리버 #준호"
  },
  "240124": {
    "text": "그룹 노매드(NOMAD), 'Automatic' 리릭비디오 공개... 2월 본격 데뷔<br><br>Group NOMAD releases lyric video for 'Automatic'... full-fledged debut in February<br><br>https://entertain.naver.com/read?oid=109&aid=0005004456<br><br>#NOMAD #노매드 <br>#DOY #SANGHA #ONE #RIVR #JUNHO <br>#도의 #상하 #원 #리버 #준호"
  },
  "240202": {
    "text": "[인터뷰] \"음악에 진심\"… 노매드의 이유있는 자신감 <br>선공개곡 5곡 순차 공개… 2월말 데뷔<br>\"구속받지 않는, 자유로운 음악 추구\"<br><br>http://naver.me/F40VC668<br><br>#NOMAD #노매드<br>#DOY #SANGHA #ONE #RIVR #JUNHO<br>#도의 #상하 #원 #리버 #준호"
  },
  "240206": {
    "text": "NOMAD 노매드 1ST EP \"NOMAD\"<br>TEASER IMAGE #2<br><br>2024.02.28 <br>1ST EP \"NOMAD\" RELEASE<br><br>#NOMAD #노매드<br>#DOY #SANGHA #ONE #RIVR #JUNHO<br>#도의 #상하 #원 #리버 #준호"
  },
  "240207": {
    "1": {
      "text": "[뉴스] 노매드, 레트로 감성 티저사진 공개... 데뷔 앨범 앞두고 기대감 UP<br><br>https://naver.me/5fPuoyV2<br><br>#NOMAD #노매드<br>#DOY #SANGHA #ONE #RIVR #JUNHO<br>#도의 #상하 #원 #리버 #준호"
    },
    "2": {
      "text": "[인터뷰] MHN 스포츠 <br><br>'신인 보이그룹' 노매드 '멤버 전원 20대? 증명할 자신 있어'[인터뷰①]<br>▶ https://naver.me/5CrS68F6<br><br>승무원-운동선수 준비하다 노매드로...데뷔 전 이렇게 뭉쳤다[인터뷰②]<br>▶ https://naver.me/xec7p52P<br><br>노매드 도의, \"음악으로 세상을 좋은 방향으로 이끄는 데 이바지하고 싶어\"<br>▶ https://naver.me/G6fG8svy<br><br>#NOMAD #노매드<br>#DOY #SANGHA #ONE #RIVR #JUNHO<br>#도의 #상하 #원 #리버 #준호"
    },
    "3": {
      "text": "Replying to <br>@NOMAD_is_here<br>[인터뷰] MHN 스포츠<br><br>신인 보이그룹 노매드, \"데뷔는 우리 이야기의 시작점\"<br>▶ https://naver.me/xUFy0M5B<br><br>#NOMAD #노매드<br>#DOY #SANGHA #ONE #RIVR #JUNHO<br>#도의 #상하 #원 #리버 #준호"
    }
  },
  "240208": {
    "text": "NOMAD 노매드<br>DEBUT CONCEPT POSTER #NOMAD<br><br>#NOMAD #노매드<br>#DOY #SANGHA #ONE #RIVR #JUNHO<br>#도의 #상하 #원 #리버 #준호"
  },
  "240210": {
    "text": "NOMAD 노매드<br>MOOD IMAGE 1 #DOY<br><br>#NOMAD #노매드<br>#DOY #SANGHA #ONE #RIVR #JUNHO<br>#도의 #상하 #원 #리버 #준호"
  },
  "240212": {
    "text": "NOMAD 노매드 1st EP <NOMAD><br>CONCEPT PHOTO 1<br><br>2024.02.28 WED 6PM (KST) <br>1st EP <NOMAD> RELEASE<br><br>#NOMAD #노매드<br>#DOY #SANGHA #ONE #RIVR #JUNHO<br>#도의 #상하 #원 #리버 #준호"
  },
  "240213": {
    "text": "NOMAD 노매드 1st EP <NOMAD><br>CONCEPT PHOTO 2 #DOY<br><br>2024.02.28 WED 6PM (KST) <br>1st EP <NOMAD> RELEASE<br><br>#NOMAD #노매드<br>#DOY #SANGHA #ONE #RIVR #JUNHO<br>#도의 #상하 #원 #리버 #준호"
  },
  "240216": {
    "text": "“떨리기보다 기대”…노매드, 직접 들려주는 데뷔 앨범 스토리<br>\"Looking forward to it rather than nervous\"... Nomad's debut album story<br><br>https://naver.me/FwSiIzyg<br><br>#NOMAD #노매드<br>#DOY #SANGHA #ONE #RIVR #JUNHO<br>#도의 #상하 #원 #리버 #준호"
  },
  "240228": {
    "1": {
      "text": "9년 연습생 끝 데뷔한 노매드 “발 닿는 곳이 무대” 자신감 가득한 출사표<br><br>https://naver.me/FKOdFjsg<br><br>#NOMAD #노매드 <br>#DOY #SANGHA #ONE #RIVR #JUNHO<br>#도의 #상하 #원 #리버 #준호"
    },
    "2": {
      "text": "“우리 곡은 우리가 만든다” 노매드, 신인답지 않은 패기<br><br>https://naver.me/5JV97cLH<br><br>#NOMAD #노매드 <br>#DOY #SANGHA #ONE #RIVR #JUNHO<br>#도의 #상하 #원 #리버 #준호"
    }
  },
  "240229": {
    "text": "BASE 여러분,<br>NOMAD의 여정이 이제 시작되었습니다. <br>첫 발걸음을 함께해 주신 BASE 여러분께 깊은 감사를 드립니다.<br><br>‘BASE’라는 소중한 팬네임은<br>다섯 멤버들의 아이디어에서 시작되었습니다.<br><br>NOMAD의 ‘Basecamp’로써, 다섯 명의 NOMAD가 향하는 방향을 알려주기도 하고 <br>다섯 명의 NOMAD가 향하는 목표를 함께 오르는 존재가 되어주시길 바라는 마음을 담아 탄생한 이름입니다.<br><br>또한 NOMAD의 근간이 되는 존재로서, <br>또 다른 ‘NOMAD’의 여섯 번째 멤버로서 앞으로도 계속 이 여정에 함께해 주시길 바랍니다.<br>감사합니다.<br><br>NOMAD & NOMAD Entertainment 드림<br><br>#NOMAD #노매드 #BASE #베이스 <br>#NOMAD_IS_HERE #BASE_IS_HERE <br>#DOY #SANGHA #ONE #RIVR #JUNHO <br>#도의 #상하 #원 #리버 #준호"
  },
  "240301": {
    "text": "2/29 Mnet 엠카운트다운 첫 데뷔 무대! ✨<br><br>#NOMAD #노매드<br>#No_pressure<br>#도의 #상하 #원 #리버 #준호<br>#DOY #SANGHA #ONE #RIVR #JUNHO"
  },
  "240302": {
    "1": {
      "text": "3/1 첫 번째 뮤직뱅크 📷<br><br>#NOMAD #노매드<br>#No_pressure<br>#도의 #상하 #원 #리버 #준호<br>#DOY #SANGHA #ONE #RIVR #JUNHO"
    },
    "2": {
      "text": "3/2 쇼!음악중심 🎤<br><br>#NOMAD #노매드<br>#No_pressure<br>#도의 #상하 #원 #리버 #준호<br>#DOY #SANGHA #ONE #RIVR #JUNHO"
    }
  },
  "240303": {
    "text": "3/3 인기가요 📸<br><br>#NOMAD #노매드<br>#No_pressure<br>#도의 #상하 #원 #리버 #준호<br>#DOY #SANGHA #ONE #RIVR #JUNHO"
  },
  "240305": {
    "1": {
      "text": "3/4 심플리 케이팝 ⏯️<br><br>#NOMAD #노매드<br>#No_pressure<br>#도의 #상하 #원 #리버 #준호<br>#DOY #SANGHA #ONE #RIVR #JUNHO"
    },
    "2": {
      "text": "3/5 더쇼 Ⓜ️<br><br>#NOMAD #노매드<br>#No_pressure<br>#도의 #상하 #원 #리버 #준호<br>#DOY #SANGHA #ONE #RIVR #JUNHO"
    }
  },
  "240307": {
    "text": "3/7 Mnet 두 번째 엠카운트다운💎<br><br>#NOMAD #노매드<br>#No_pressure<br>#도의 #상하 #원 #리버 #준호<br>#DOY #SANGHA #ONE #RIVR #JUNHO"
  },
  "240308": {
    "text": "3/8 뮤직뱅크 💰<br><br>#NOMAD #노매드<br>#No_pressure<br>#도의 #상하 #원 #리버 #준호<br>#DOY #SANGHA #ONE #RIVR #JUNHO"
  },
  "240309": {
    "1": {
      "text": "Swimmin' to you<br><br>#NOMAD #노매드<br>#DOY #SANGHA #ONE #RIVR #JUNHO<br>#도의 #상하 #원 #리버 #준호"
    },
    "2": {
      "text": "3/9 쇼!음악중심 <br><br>#NOMAD #노매드<br>#No_pressure<br>#도의 #상하 #원 #리버 #준호<br>#DOY #SANGHA #ONE #RIVR #JUNHO"
    }
  },
  "240311": {
    "text": "'수영장 콘셉트' 노매드, 1st EP 'NOMAD' Cali 버전 플랫폼 앨범 발매<br><br>https://naver.me/xb73G085<br><br>#NOMAD #노매드<br>#California_love"
  },
  "240312": {
    "1": {
      "text": "NOMAD 노매드 1st EP <NOMAD> <br>Cali ver<br><br>CONCEPT PHOTO 2<br><br>2024.03.13 WED 6PM (KST)  <br>'California love' MV RELEASE  <br><br>#NOMAD #노매드 <br>#DOY #도의"
    },
    "2": {
      "text": "3/12 더쇼✨<br><br>#NOMAD #노매드 <br>#No_pressure <br>#DOY #SANGHA #ONE #RIVR #JUNHO <br>#도의 #상하 #원 #리버 #준호"
    }
  },
  "240313": {
    "text": "노매드, '캘리포니아 러브' 뮤비 공개…실제 캘리포니아 올로케<br><br>https://naver.me/x0zAQIwA<br><br>#NOMAD #노매드<br>#California_love"
  },
  "240314": {
    "text": "3/13 쇼!챔피언<br><br>#NOMAD #노매드<br>#No_pressure #California_love<br>#DOY #SANGHA #ONE #RIVR #JUNHO<br>#도의 #상하 #원 #리버 #준호"
  },
  "240315": {
    "text": "3/15 뮤직뱅크<br><br>#NOMAD #노매드<br>#CaliforniaLove #캘리포니아러브<br>#DOY #SANGHA #ONE #RIVR #JUNHO<br>#도의 #상하 #원 #리버 #준호"
  },
  "240316": {
    "text": "3/16 쇼! 음악중심<br><br>#NOMAD #노매드<br>#CaliforniaLove #캘리포니아러브<br>#DOY #도의"
  },
  "240317": {
    "text": "3/17 인기가요<br><br>#NOMAD #노매드<br>#CaliforniaLove #캘리포니아러브 <br>#DOY #도의"
  },
  "240319": {
    "text": "3/19 더쇼<br><br>#NOMAD #노매드<br>#CaliforniaLove #캘리포니아러브 <br>#DOY #SANGHA #ONE #RIVR #JUNHO <br>#도의 #상하 #원 #리버 #준호"
  },
  "240321": {
    "text": "3/20 쇼챔피언<br><br>#NOMAD #노매드<br>#CaliforniaLove #캘리포니아러브 <br>#DOY #SANGHA #ONE #RIVR #JUNHO <br>#도의 #상하 #원 #리버 #준호"
  },
  "240328": {
    "text": "3/27 1st EP 마지막 쇼챔피언✨<br><br>#NOMAD #노매드<br>#CaliforniaLove #캘리포니아러브 <br>#DOY #SANGHA #ONE #RIVR #JUNHO <br>#도의 #상하 #원 #리버 #준호"
  },
  "240402": {
    "text": "[#상하] <br><br>NOMAD was here!<br>멤버들과 함께 에버라인 팝업에 다녀왔어요 <br>저희 앨범과 사진이 전시되어 있는게 너무 신기하고 감사했어요 =) <br>멤버들이랑 여기저기에 낙서도 하구 포토카드에 사인도 해서 숨겨놨으니까 베이스들 와서 꼭 찾아줘요!! <br>저희보다 먼저 방문해 주신 분들도 너무 너무 감사합니당 남겨주신 포스트잇도 다 읽었어요!ㅎㅎ<br>내일 올 베이스도, 바빠서 혹은 멀어서 오지 못하는 베이스도, <br>모든 베이스에게 행운이 가득하길 바라요<br>그럼 굿밤😌🤍<br><br>#NOMAD #노매드<br>#DOY #SANGHA #ONE #RIVR #JUNHO<br>#도의 #상하 #원 #리버 #준호"
  },
  "240404": {
    "text": ""
  },
  "240410": {
    "text": "[#원]<br><br>오늘 만난 베이스들 모두 안전히 돌아갔죠?? <br>데뷔가 엊그제 같은데 오늘이 첫 앨범 마지막 팬사인회라니 너무 아쉬워요😭 <br><br>첫 번째 활동은 마무리 되었지만 앞으로 저희 소통도 많이 하고 직접 만날 기회도 많이 만들테니 기대해 주세요! 오늘 못 본 베이스들도 조만간 봐요!!<br><br>p.s. 베이스가 보내주신 피자 너무 맛있게 잘 먹었습니다 진짜 최근에 먹은 피자 중에 제일 맛있었어요..<br><br>#NOMAD #노매드<br>#DOY #SANGHA #ONE #RIVR #JUNHO<br>#도의 #상하 #원 #리버 #준호"
  },
  "240418": {
    "text": "NOMAD 2024 SHOWCASE IN JAPAN<br>💌 a message from NOMAD! <br><br>🗓️ 4/23 Tue TOKYO@Spotify O-EAST       <br> 1st 16:00 / 2nd 20:00  <br>🗓️ 4/25 Thu OSAKA@GORILLA HALL<br> 1st 16:00 / 2nd 20:00<br><br>🎫 http://eplus.jp/nomad/<br>* The online reservation for the Tokyo concert has ended, so you can visit the concert hall on the same day and purchase tickets.<br><br>#NOMAD #노매드<br>#DOY #SANGHA #ONE #RIVR #JUNHO<br>#도의 #상하 #원 #리버 #준호"
  },
  "240426": {
    "text": "2024 SHOWCASE IN JAPAN <br>おわり!<br>BASE、ありがとうございます。<br><br>#NOMAD #노매드<br>#NOMADishere<br>#DOY #SANGHA #ONE #RIVR #JUNHO<br>#도의 #상하 #원 #리버 #준호"
  },
  "240429": {
    "text": "JAPAN SHOWCASE <br>Behind the stage 📸<br><br>#NOMAD #노매드<br>#DOY #SANGHA #ONE #RIVR #JUNHO<br>#도의 #상하 #원 #리버 #준호"
  },
  "240505": {
    "text": "[EVENT]<br><br>어린이날 기념 SPECIAL EVENT<br>어린이 NOMAD 사진을 보고 멤버 맞히기🔎<br><br>정답자 중, 추첨을 통해<br>NOMAD 사인 폴라로이드를 드립니다.<br>팬 여러분의 많은 참여 바랍니다!<br><br>#NOMAD #노매드 #Baby_NOMAD<br>#DOY #SANGHA #ONE #RIVR #JUNHO<br>#도의 #상하 #원 #리버 #준호"
  },
  "240514": {
    "text": ""
  },
  "240515": {
    "text": "[INTERVIEW]<br>#OBS 독특한 연예뉴스<br><br>어디서도 들을 수 없었던 이야기...'5인 5색' 노매드의 매력<br><br>🎬 https://youtu.be/mIZW4lpsOTc?si=OBWR2DgmEzwv2ypQ<br><br>#NOMAD #노매드 <br>#DOY #SANGHA #ONE #RIVR #JUNHO <br>#도의 #상하 #원 #리버 #준호"
  },
  "240516": {
    "text": "5/16 음악 실연자 페스티벌 <br><br>#NOMAD #노매드<br>#NOMAD_is_here #KMPF2024 #KMPF<br>#DOY #SANGHA #ONE #RIVR #JUNHO<br>#도의 #상하 #원 #리버 #준호"
  },
  "240530": {
    "text": "[LIVE] NOMAD DEBUT ❶⓿⓿ DAYS 100분 라이브!<br><br>NOMAD와 BASE가 함께 달려온 100일🏃<br>같이 모여 축하해 주세요!<br><br>⏰ 2024년 6월 6일 오후 8시 20분 (KST)<br> - 1부 : 공식 인스타그램 라이브<br> - 2부 : 공식 팬 플랫폼 라이브 팝* <br>  * 0원 이용권을 구매하신 분만 시청이 가능합니다.<br>  🎫 0원 이용권 구매하기 : https://nomadofficial.kr/shop/kr/products/5<br><br>#NOMAD_DEBUT_100DAYS <br>#NOMAD데뷔100일<br>#NOMAD_WITH_BASE_100DAYS<br><br>#NOMAD #노매드<br>#DOY #SANGHA #ONE #RIVR #JUNHO<br>#도의 #상하 #원 #리버 #준호"
  },
  "240606": {
    "1": {
      "text": "HAPPY 100 DAYS NOMAD!<br><br>#NOMAD_DEBUT_100DAYS <br>#NOMAD데뷔100일<br>#NOMAD_WITH_BASE_100DAYS<br><br>#NOMAD #노매드<br>#DOY #SANGHA #ONE #RIVR #JUNHO<br>#도의 #상하 #원 #리버 #준호"
    },
    "2": {
      "text": "[#도의]<br>100분 라이브 봐줘서 고마워요 베이스!<br>100일동안 사랑해주셔서 감사합니다.<br>Doy was here🙄<br>NOMAD was here🤔<br>BASE was here🤭<br><br>#NOMAD_DEBUT_100DAYS <br>#NOMAD데뷔100일<br>#NOMAD_WITH_BASE_100DAYS<br><br>#NOMAD #노매드<br>#DOY #SANGHA #ONE #RIVR #JUNHO<br>#도의 #상하 #원 #리버 #준호"
    }
  },
  "240614": {
    "text": "그룹 노매드(NOMAD), 멕시코시티에서 K-POP 전파 나선다<br><br>https://naver.me/FafMVu81<br><br>#NOMAD #노매드<br>#DOY #SANGHA #ONE #RIVR #JUNHO<br>#도의 #상하 #원 #리버 #준호"
  },
  "240617": {
    "text": "2024 K-BRAND EXPO IN MEXICO<br>Muchas gracias BASE Mexicana!<br><br>#NOMAD #노매드<br>#DOY #SANGHA #ONE #RIVR #JUNHO<br>#도의 #상하 #원 #리버 #준호"
  },
  "240619": {
    "text": "📷 Behind cut<br><br>2024 K-BRAND EXPO IN MEXICO<br>Ambassador NOMAD (Opening Ceremony)<br><br>#NOMAD #노매드<br>#DOY #SANGHA #ONE #RIVR #JUNHO<br>#도의 #상하 #원 #리버 #준호"
  },
  "240704": {
    "text": "[#리버]  <br>베이스 여러분 저희 노가리 팟캐스트 첫 촬영분 재밌게 즐기셨는지요 ~_~ <br>다음 노가리는 더욱 재미있는 주제로 빠른 시일 내에 돌아오겠습니다!! <br>그 때까지 조회수 20만..을 달성할 수 있길 바라며.. <br>오늘도 편안한 밤 되세요😌  <br><br>#NOMAD #노매드 #NoGotIt #노가리 <br>#RIVR #리버"
  },
  "240725": {
    "text": "Replying to <br>@NOMAD_is_here<br>#노매드_드림루키2차투표 인증 이벤트 <br>2등 선물 공개! <br><br>전 멤버 폴라로이드 세트<br>+ 🎁 미공개 단체 포토이즘 사진 🎁<br><br>#NOMAD #노매드<br>#NOMAD_is_here #드림루키 #DREAMROOKIE<br>#노매드_드림루키2차투표<br>#NOMAD_DreamRookie_Round2<br>#DOY #SANGHA #ONE #RIVR #JUNHO<br>#도의 #상하 #원 #리버 #준호"
  },
  "240727": {
    "text": "노매드가 포토이즘 찍는 법.jpg 📸<br><br>#NOMAD #노매드<br>#NOMAD_is_here #드림루키 #DREAMROOKIE<br>#노매드_드림루키2차투표<br>#NOMAD_DreamRookie_Round2<br>#DOY #SANGHA #ONE <br>#도의 #상하 #원"
  },
  "240730": {
    "text": ""
  },
  "240731": {
    "text": "노매드_포토이즘_포즈추천_트위터ver.mp4<br><br>#NOMAD #노매드<br>#NOMAD_is_here #드림루키 #DREAMROOKIE<br>#노매드_드림루키2차투표<br>#NOMAD_DreamRookie_Round2<br>#DOY #SANGHA #ONE #RIVR #JUNHO<br>#도의 #상하 #원 #리버 #준호"
  },
  "240807": {
    "1": {
      "text": "노매드의 노빠꾸(NO BACK GO) EP.poster<br><br>그동안 베일에 쌓였던 노매드의 직진본능!<br>이제 그들의 뜨거운 이야기가 펼쳐집니다.<br><br>2024.08.15 EP.01 첫 방송<br>NOMAD OFFICIAL 유튜브 채널에서 만나보세요! 👀<br>놓치면 후회할 걸?🚀<br><br>#NOMAD #노매드<br>#DOY #SANGHA #ONE #RIVR #JUNHO<br>#도의 #상하 #원 #리버 #준호<br>#노매드의_노빠꾸 #NOMAD_NOBACKGO"
    },
    "2": {
      "text": ""
    }
  },
  "240815": {
    "text": "MZ 노매드랑 🖤 MZ 베이스랑<br><br>#NOMAD #노매드"
  },
  "240822": {
    "text": ""
  },
  "240824": {
    "text": "<NOMAD와 함께하는 포토이즘 데이트><br>이벤트 완료🖤<br><br>2차 투표에 참여해 주신 모든 BASE 분들께 다시 한번 감사드립니다.<br><br>3차 투표 이벤트도 많은 관심 부탁 드립니다🙇🏻‍♀️<br><br>@photoism_kr<br><br><br>#NOMAD #노매드<br>#NOMAD_is_here<br>#드림루키 #DREAMROOKIE"
  },
  "240826": {
    "text": "#NOGOTITwithBASE<br>노매드에게 무엇이든 물어보세요! 당첨자 발표<br><br>다양하고 재미있는 질문을 보내주신<br>모든 BASE 분들께 감사드립니다. <br><br>멤버들이 직접 고른 베스트 질문은<br>영상을 통해 확인해주세요! <br><br>멤버들의 불꽃튀겼던 논쟁 풀 영상은<br>8월 27일 00시! NOMAD 공식 유튜브 채널 '노가리(NO! GOT IT!)' 에서 만나보실 수 있습니다.<br>많은 기대 부탁드립니다! 😎 <br><br>* 당첨자분들은 리워드 수령을 위해 개별 DM을 확인 부탁드립니다. <br><br>#NOGOTITwithBASE<br>#NOMAD #노매드"
  },
  "240905": {
    "text": "BASE와 함께한 노가리(NO GOT! IT!) EP.08<br>재밌게 보셨나요?<br><br>앞으로도 노매드의 노가리는<br>팩트만 보여드리겠습니다 ‼<br> ㄴ 퍼펙트 🤭🖤<br><br>#NOMAD #노매드<br>#NOGOTITwithBASE"
  },
  "240906": {
    "text": "노매드의 노빠꾸(NO BACK GO) EP.poster<br><br>본격적으로 시작되는 노빠꾸 ❗<br>빠꾸없는 노매드의 여름방학 이야기 🚎💨<br><br>2024.09.13 EP.03 <br>NOMAD OFFICIAL 유튜브 채널에서 만나보세요! <br>놓치면 아쉬울 걸?🚀<br><br>#NOMAD #노매드<br>#DOY #SANGHA #ONE #RIVR #JUNHO<br>#도의 #상하 #원 #리버 #준호<br>#노매드의_노빠꾸 #NOMAD_NOBACKGO"
  },
  "240911": {
    "text": "[NEWS]<br><br>노매드, 10월 싱글 1집으로 컴백 확정<br>https://m.entertain.naver.com/article/144/0000987938<br><br>#NOMAD #노매드"
  },
  "240912": {
    "text": "[NEWS]<br><br>노매드, 2024 도쿄 한류 박람회 아시아 루키 선정…\"떠오르는 글로벌 아티스트 증명\"<br>https://m.entertain.naver.com/article/477/0000511861<br><br>#NOMAD #노매드"
  },
  "240914": {
    "text": "HAPPY 200 DAYS NOMAD!<br><br>#NOMAD_DEBUT_200DAYS<br>#NOMAD데뷔200일<br>#NOMAD_WITH_BASE_200DAYS<br><br>#NOMAD #노매드<br>#DOY #SANGHA #ONE #RIVR #JUNHO<br>#도의 #상하 #원 #리버 #준호"
  },
  "240916": {
    "1": {
      "text": "HAPPY BIRTHDAY DOY 🎂<br><br>#HappyDOYday<br>#NOMAD #노매드<br>#DOY #도의"
    },
    "2": {
      "text": "Can you Call Me Back?<br><br>#NOMAD #노매드"
    }
  },
  "240920": {
    "text": "NOMAD 1st Single<br>【𝓒𝓪𝓵𝓵 𝓜𝓮 𝓑𝓪𝓬𝓴】<br><br>📞 2024.10.09 6PM (KST)<br><br>#NOMAD #노매드<br>#CallMeBack #NOMAD_CallMeBack<br>#NOMAD_20241009"
  },
  "240924": {
    "text": "NOMAD 1st Single<br>【𝓒𝓪𝓵𝓵 𝓜𝓮 𝓑𝓪𝓬𝓴】<br><br>📞𝗖𝗮𝗻 𝗬𝗼𝘂 𝗖𝗮𝗹𝗹 𝗠𝗲 𝗕𝗮𝗰𝗸? <br><br>🇰🇷 070-4517-0228<br>🌐+8270-4517-0228 <br>📅 2024.09.29 15:00 (KST)<br><br>#NOMAD #노매드<br>#CallMeBack #NOMAD_CallMeBack<br>#NOMAD_20241009"
  },
  "240927": {
    "text": "NOMAD 1st Single<br>【𝓒𝓪𝓵𝓵 𝓜𝓮 𝓑𝓪𝓬𝓴】<br><br>CONCEPT PHOTO #DOY<br><br>📞 2024.10.09 6PM (KST)<br><br>#NOMAD #노매드<br>#도의<br>#CallMeBack #NOMAD_CallMeBack<br>#NOMAD_20241009"
  },
  "240928": {
    "text": "NOMAD 1st Single<br>【𝓒𝓪𝓵𝓵 𝓜𝓮 𝓑𝓪𝓬𝓴】<br><br>CONCEPT PHOTO #NOMAD<br><br>📞 2024.10.09 6PM (KST)<br><br>#노매드<br>#CallMeBack #NOMAD_CallMeBack<br>#NOMAD_20241009"
  },
  "240929": {
    "text": "[📞] Can You Call Me Back? 이벤트 종료‼️<br><br>멤버들과 깜짝 통화 다들 즐거우셨나요? 🤔<br><br>통화량이 많아 통신이 불안정했던 점<br>너른 양해부탁드리며 노매드의 콜미백🤙<br>많은 관심 부탁드립니다.🖤<br><br>#NOMAD #노매드<br>#CallMeBack #NOMAD_CallMeBack<br>#NOMAD_20241009"
  },
  "240930": {
    "text": "[NEWS]<br><br>노매드, 첫 싱글 '콜미백' 베일 벗었다…콘셉트 공개<br>https://m.entertain.naver.com/article/477/0000514416<br><br>#NOMAD #노매드"
  },
  "241009": {
    "text": "NOMAD [Call Me Back] 리스닝파티 후기<br>별 : ★★★★★ x 240228<br>어서 빨리 전화해죠~~~📞😉<br><br>#NOMAD #노매드<br>#CallMeBack #NOMAD_CallMeBack"
  },
  "241010": {
    "text": "[📞] 이수👫 만났던<br>오늘이🎶 꿈🛌🌙 같았어🖤<br><br>#NOMAD #노매드<br>#CallMeBack #NOMAD_CallMeBack"
  },
  "241011": {
    "text": "플레이어이자 프로듀서인 노매드(NOMAD)가 직접 전하는 첫 싱글 [Call Me Back] 작업 비하인드<br><br>➫ https://kko.to/iveRrbO1_e  <br><br>#NOMAD #노매드<br>#CallMeBack #NOMAD_CallMeBack"
  },
  "241012": {
    "text": "[📞] 2024 도쿄 한류 박람회<br>일본에서의 첫 Call Me Back <br>早く電話して😝🤙<br><br>#NOMAD #노매드<br>#CallMeBack #NOMAD_CallMeBack"
  },
  "241013": {
    "text": "[📞]<br>나만의 블랙스완 🖤 𝐍𝐎𝐌𝐀𝐃 🖤 <br>당신을 보고 첫 눈에 반했습니다.<br><br>010-xxxx-0228 <br>‘콜미백‘🤙<br><br>#NOMAD #노매드<br>#CallMeBack #NOMAD_CallMeBack"
  },
  "241014": {
    "text": "[📞]<br>노매드 첫 라디오❗️<br>다들 잘 보셨나요?🤔<br><br>사녹부터 라디오까지<br>언제 어디서나 BASE 응원은<br>완전 로스트치킨이야🫶🏻 <br><br>#NOMAD #노매드<br>#CallMeBack #NOMAD_CallMeBack"
  },
  "241015": {
    "text": "[📞]<br>성경배우님 만난<br>2024 KBEE 박람회가<br>꿈 같았어..😌🌙<br><br>#NOMAD #노매드<br>#CallMeBack #NOMAD_CallMeBack"
  },
  "241016": {
    "text": "[📞]<br>다른 건 모르겠고.<br>딱 한마디만 하겠습니다.<br><br>＿人人人＿<br>＞베이스최고＜<br>￣Y^Y^Y￣<br>　 _n<br>　( ｜　 ハ_ハ<br>　 ＼＼ ( ‘-^　)<br>　　 ＼￣￣   )<br>　　　７　 /<br><br>#NOMAD #노매드<br>#CallMeBack #NOMAD_CallMeBack"
  },
  "241017": {
    "text": "[📞]<br>오늘의 노매드<br>완벽매드😎<br><br>오늘의 BASE<br>사랑이수🖤<br><br>#NOMAD #노매드<br>#CallMeBack #NOMAD_CallMeBack"
  },
  "241018": {
    "text": "[📞]<br>찬란했던 Memories 🎤<br>이수는 그저 노매드에게 좋은 향기로🌸<br>Just make it up to me <br><br>#NOMAD #노매드<br>#CallMeBack #NOMAD_CallMeBack"
  },
  "241019": {
    "text": "[📞]<br>우리 BASE는 언제부터<br>그렇게 예뻤나?🥰<br><br>오늘 하루도 BASE Chek✅<br>완료‼️<br><br>#NOMAD #노매드<br>#CallMeBack #NOMAD_CallMeBack"
  },
  "241020": {
    "text": "[📞]<br><br>🎵이수는 대학 시절<br>노매드를 전공했단 사실~🎶<br><br>오늘도 Ⓗⓐⓟⓟⓨ 매드가 되🤍 <br><br>#NOMAD #노매드<br>#CallMeBack #NOMAD_CallMeBack"
  },
  "241022": {
    "text": "[NEWS]<br><br>노매드, 도쿄 한류 박람회서 '아시아 루키' 입증<br>https://m.entertain.naver.com/article/477/0000518075<br><br>#NOMAD #노매드"
  },
  "241024": {
    "text": "[📞]<br><br>✮ *       ˚        .            ⁺           ˚ <br>.  \" 좋아한다? 아닌데, 베이스 사랑하는데 <br>      오늘도 전화해줘서 고마워요 🤙\" ｡𖤐<br>     ⁺                   ˚          ⁺           . ⋆⁺₊⋆<br><br>#NOMAD #노매드<br>#CallMeBack #NOMAD_CallMeBack"
  },
  "241026": {
    "text": "[📞]<br><br>주말 아침에 일어나서 제일 먼저 하는 것<br>✔️ POP으로 굿모닝 인사하기<br>✔️ 베이스 보기 🥰<br><br>행복한 주말 보내요 🩵<br><br>#NOMAD #노매드<br>#CallMeBack #NOMAD_CallMeBack"
  },
  "241027": {
    "text": "[📞]<br>✨노매드의 𝐒𝐩𝐞𝐜𝐢𝐚𝐥 𝐃𝐚𝐲 ✨<br><br>이수 낭자를 만나서 반가웠소.<br>나는 BASE를 보면 웃음을 참지 못하는 병이있어. <br>926년을 살면서 가장 행복한 날이었어.<br>BASE는 영원한 나의 친구야.<br>항상 베이스들이 행복과 평안을<br>찾아 가길 소망합니다.🩶<br><br>#NOMAD #노매드<br>#CallMeBack #NOMAD_CallMeBack"
  },
  "241030": {
    "text": "[📞]<br>오늘 하루도 고생한 베이스에게<br>선사하는 # 오늘의_노매드 🎁<br><br>또 Call Me Back 해주기 〰️🤙<br><br>#NOMAD #노매드<br>#CallMeBack #NOMAD_CallMeBack"
  },
  "241031": {
    "text": ""
  },
  "241101": {
    "1": {
      "text": "[📞]<br>KOREA BRAND EXPO<br>사우디아라비아에서<br>Call Me Back 전파 완료✌🏻<br><br>Thank you<br>Saudi Arabia👏👏👏<br><br>#NOMAD #노매드<br>#CallMeBack #NOMAD_CallMeBack"
    },
    "2": {
      "text": "[📞]<br>콜미백 콜센터에 전화주셔서<br>감사합니다. ☎️<br><br>🩵 지금 전화 받는 노매드는<br>베이스에게 소중한 사람입니다.🩵<br><br>#NOMAD #노매드<br>#CallMeBack #NOMAD_CallMeBack"
    }
  },
  "241102": {
    "text": "[📞]<br>NOMAD in 🇸🇦<br>이틀간 함께해주셔서 감사했어요!<br><br>사우디아라비아<br>또 만나요👋 슈크란💚 <br><br>#NOMAD #노매드<br>#CallMeBack #NOMAD_CallMeBack"
  },
  "241103": {
    "text": "[📞]<br>#누구보다_빠른_11월_최애_선점<br>11월 첫 Call Me Back🤙<br><br>이번 달도 잘 부탁해 베이스~😉<br><br>#NOMAD #노매드<br>#CallMeBack #NOMAD_CallMeBack"
  },
  "241105": {
    "text": "[📢] 𝗡𝗢𝗠𝗔𝗗 𝗜𝗦 𝗛𝗘𝗥𝗘 𝗶𝗻 𝗛𝗼𝗻𝗴𝗱𝗮𝗲<br><br>NOMAD의 첫 BUSKING #홍대 🎵<br><br>📍 2024.11.09 SAT 16:00 ~ <br>📍 홍대 버스킹 4존<br><br>➫ https://nomadofficial.kr/community/board/65c1c8d06a758c09850c7003/post/6729dec4faf4c54bdec9f943<br>자세한 내용은 비스테이지를 확인해주세요‼️<br><br>#NOMAD #노매드<br>#CallMeBack #NOMAD_CallMeBack"
  },
  "241106": {
    "text": "[📞]<br>K-pop Star Showcase ✨<br>노매드씨 축하드려요<br> ㄴ 오늘도 잘생기신거 축하드립니다.👏👏<br><br>#NOMAD #노매드<br>#CallMeBack #NOMAD_CallMeBack"
  },
  "241107": {
    "text": "[NEWS]<br><br>노매드, '콜 미 백' 발매기념 버스킹 나선다…9일 홍대 인근<br>https://spotvnews.co.kr/news/articleView.html?idxno=713804<br><br>#NOMAD #노매드"
  },
  "241108": {
    "1": {
      "text": "노매드의 노빠꾸(NO BACK GO) EP.poster<br><br>다시 돌아온 노빠꾸‼️<br>우리 회사에 이런 상사 있었으면 어떨 거 같음?<br><br>2024.11.15 EP.05<br>NOMAD OFFICIAL 유튜브 채널에서 만나보세요! 👀<br><br>#NOMAD #노매드<br>#노매드의_노빠꾸 #NOMAD_NOBACKGO"
    },
    "2": {
      "text": "[📞]<br>노□Й드 LIㄱr<br>베○l스으l 별○l⊂ト<br><br>＜우zl으lАŁㄹБ포러l버★＞<br><br>#NOMAD #노매드<br>#CallMeBack #NOMAD_CallMeBack"
    }
  },
  "241109": {
    "text": "[📞]<br>충격❗️ 쉐프매드 실존 👀<br><br>오늘도 노매드의 베이스 사랑은<br>이븐하게 익었네요 🖤<br><br>#NOMAD #노매드<br>#CallMeBack #NOMAD_CallMeBack"
  },
  "241110": {
    "text": "[📞]<br>노매드 학교 등교 완료 🏫<br>노매드 학교에 베이스의 등장이라😏<br><br>리버 : 오늘 야자 쨀 사람 ~ 🙌🏻<br><br>#NOMAD #노매드<br>#CallMeBack #NOMAD_CallMeBack"
  },
  "241112": {
    "1": {
      "text": "[단독] 노매드, 덕력고사 시험 현장‼️<br><br>#NOMAD #노매드<br>#CallMeBack #NOMAD_CallMeBack"
    },
    "2": {
      "text": "[속보] 노매드, 덕력고사 시험지 유출! 만점자 없어 소속사 황당,, <br><br>#NOMAD #노매드<br>#CallMeBack #NOMAD_CallMeBack"
    }
  },
  "241113": {
    "text": "[📞]<br>월요일 : 짱싫음<br>화요일 : 싫음<br>수요일 : ♥노매드랑 콜미백 하는 날 ♥<br> ㄴ 왕왕좋음<br><br>#NOMAD #노매드<br>#CallMeBack #NOMAD_CallMeBack"
  },
  "241114": {
    "text": "[NEWS] 노매드, 사우디 달궜다…2024 코리아 브랜드 엑스포 홍보대사 선정<br><br>https://m.entertain.naver.com/article/477/0000521673<br><br>#NOMAD #노매드"
  },
  "241115": {
    "text": "[NEWS] 노매드, 데뷔 첫 버스킹 성료…400여명 몰려 성황<br><br>https://m.entertain.naver.com/article/477/0000521952<br><br>#NOMAD #노매드"
  },
  "241117": {
    "text": "[📞]<br>노매드는 자카르타에서 열정핑😎<br>후기 : ⭐️⭐️⭐️⭐️⭐️<br> ㄴ 노매드가 멋있고 자카르타 열정 대단해요😍🇮🇩<br><br>#NOMAD #노매드<br>#CallMeBack #NOMAD_CallMeBack"
  },
  "241119": {
    "text": "[📞]<br><br>오늘도 고생한 베이스🫶🏻<br>노매드는 베이스봐서 충전완료🔋<br><br>🗣️ 원메추) 오늘은 족발드세요‼️<br><br>#NOMAD #노매드<br>#CallMeBack #NOMAD_CallMeBack"
  },
  "241121": {
    "text": "[NEWS] 노매드, 인도네시아 달궜다… 현지 팬 5000명 '열광'<br><br>https://m.entertain.naver.com/article/477/0000522608<br><br>#NOMAD #노매드"
  },
  "241122": {
    "text": "[📞]<br>불타는 금요일 🔥<br>노매드도 불타는 영상통화 완료 📞<br><br>#NOMAD #노매드<br>#CallMeBack #NOMAD_CallMeBack"
  },
  "241123": {
    "text": "[📞]<br>충격‼️수트매드 실존 😎<br>노매드를 향한 무조건적인 박수갈채<br>일방적이고 편향적인 칭찬<br>부탁드립니다.🖤<br><br>#NOMAD #노매드<br>#CallMeBack #NOMAD_CallMeBack"
  },
  "241124": {
    "text": "[📞]<br>노매드는 오늘부터 베이스를 향한 마음을 접습니다..<br>가로 세로 반을 접은 후 펴줍니다.<br>뒤집어서 세로선을 따라 접어 삼각형을 만든 뒤<br>양쪽 날개 부분을 가운데 선을 따라 반으로 접어주면<br>예쁜 하트 접기 완성 🖤<br><br>#NOMAD #노매드<br>#CallMeBack #NOMAD_CallMeBack"
  },
  "241128": {
    "text": "[📞]<br>기온별 옷차림<br>22~20도: 긴팔티, 면바지, 슬랙스<br>19~17도: 가디건, 니트, 맨투맨, 후드, 긴바지<br>16~12도: 자켓, 가디건, 청자켓, 니트<br>11~9도: 코트, 점퍼, 기모바지<br>8~5도: 히트텍, 기모<br>4도 이하: 노매드 품 속으로 들어가기<br><br>#NOMAD #노매드<br>#CallMeBack #NOMAD_CallMeBack"
  },
  "241130": {
    "text": "[📞]<br>파자마 입고 ~ 피자마 입고 ~<br>우리 오늘 밤 멋진 파티를 해요 🕺💃🏻🕺💃🏻<br>파자마매드와 함께 미리 굿나잇 🌙<br><br>#NOMAD #노매드<br>#CallMeBack #NOMAD_CallMeBack"
  },
  "241201": {
    "text": "[📞]<br>추운 겨울 노매드를 따듯하게 하는 것<br>핫팩 ❌<br>붕어빵 ❌<br>롱패딩 ❌<br>바로 베이스의 사랑 ♥️<br><br>#NOMAD #노매드 <br>#CallMeBack #NOMAD_CallMeBack"
  },
  "241203": {
    "text": "[NEWS]<br><br>노매드, 한국 e스포츠산업 학회 명예 홍보대사 위촉<br>https://m.entertain.naver.com/article/477/0000524324<br><br>#NOMAD #노매드"
  },
  "241207": {
    "1": {
      "text": "[📞]<br>12월 첫 팬사인회☺️<br>베이스 덕분에 따뜻한 금요일<br>n 3^07 ! 🖤<br><br>#NOMAD #노매드<br>#CallMeBack #NOMAD_CallMeBack"
    },
    "2": {
      "text": "[📞]<br>베이스와 함께 미라클모닝 팬사인회☀️<br>주말 잘 보내기 🤙🖤<br><br>#NOMAD #노매드<br>#CallMeBack #NOMAD_CallMeBack"
    }
  },
  "241212": {
    "text": "[📞]<br>기억해,, 춥지만 따뜻했던 오늘..<br>베이스와 영상통화로 만난 날 🖤<br><br>#NOMAD #노매드<br>#CallMeBack #NOMAD_CallMeBack"
  },
  "241213": {
    "text": "NOMAD Christmas <MISTLETOE.cover><br>FILM MOOD 📷 #2<br><br>#NOMAD #노매드"
  },
  "241214": {
    "text": "[📞]<br>주말에 베이스랑 <br>따뜻한 주말 보내기 🫶🏻<br><br>#NOMAD #노매드<br>#CallMeBack #NOMAD_CallMeBack"
  },
  "241215": {
    "text": "[📞]<br>이번 주도 고생했어요<br>🫳🫳🫳<br>베  이  스 🖤<br>다가오는 연말도 노매드와 함께해 주기😉<br><br>#NOMAD #노매드<br>#CallMeBack #NOMAD_CallMeBack"
  },
  "241218": {
    "1": {
      "text": "[📞]<br>베이스와 함께하는 모든 날들이<br>행복했다 🤎<br><br>#NOMAD #노매드<br>#CallMeBack #NOMAD_CallMeBack"
    },
    "2": {
      "text": ""
    }
  },
  "241220": {
    "text": "[📞]<br>𝗡𝗢𝗠𝗔𝗗 𝗜𝗦 𝗛𝗘𝗥𝗘 𝗶𝗻 𝘀𝗰𝗵𝗼𝗼𝗹<br>NOMAD의 첫 스쿨어택 #동일여고 🎵<br><br>‘더브러하나’ 함께 즐겨주셔서 감사합니다🫶🏻<br><br>#NOMAD #노매드<br>#NOMAD_IS_HERE_in_school  <br>#CallMeBack #NOMAD_CallMeBack"
  },
  "241221": {
    "text": "[📞]<br>직업매드와 함께한 토요일 😊<br>느낌 좋은 노매드와 함께 좋은 주말보내요 🖤<br><br>#NOMAD #노매드<br>#CallMeBack #NOMAD_CallMeBack"
  },
  "241222": {
    "text": "[📞]<br>베이스와 함께한 첫<br>미리메리크리스마스 🎅🎄<br><br>#NOMAD #노매드<br>#CallMeBack #NOMAD_CallMeBack"
  },
  "241223": {
    "text": "🖤 𝐍𝐎𝐌𝐀𝐃 𝐃𝐄𝐁𝐔𝐓 𝟑𝟎𝟎𝐃𝐀𝐘𝐒 🖤<br><br>#NOMAD #노매드 <br><br>#NOMAD_DEBUT_300DAYS #NOMAD데뷔300일<br>#NOMAD_WITH_BASE_300DAYS"
  },
  "241224": {
    "text": "[📞]<br>𝗡𝗢𝗠𝗔𝗗 𝗜𝗦 𝗛𝗘𝗥𝗘 𝗶𝗻 𝘀𝗰𝗵𝗼𝗼𝗹<br>NOMAD의 스쿨어택 #덕성여고 & #한성여고 🎵<br><br>크리스마스 이브 날 큰 에너지 받았습니다! 🫶🏻<br><br>#NOMAD #노매드<br>#NOMAD_IS_HERE_in_school  <br>#CallMeBack #NOMAD_CallMeBack"
  },
  "241225": {
    "1": {
      "text": "Merry NOMADmas  FILM MOOD 📷<br><br>#NOMAD #노매드<br>#Christmas"
    },
    "2": {
      "text": "[📞]<br>베이스와 맞이한 첫 크리스마스<br>언제 어디서든 함께해줘서 고마워요<br>남은 하루 행복하게 보내요<br>메리크리스마스🎅🎄<br><br>#NOMAD #노매드<br>#CallMeBack #NOMAD_CallMeBack"
    }
  },
  "241227": {
    "text": "[📞]<br>베이스가 웃으면 노매드도 좋아 😉<br>남은 연말도 노매드와 베이스 웃음만 가득하길..⭐<br><br>#NOMAD #노매드<br>#CallMeBack #NOMAD_CallMeBack"
  },
  "241228": {
    "text": "[📞]<br>낭자, 낭군들 오늘의 담소도 즐거웠소<br>그대들에게 좋은 하루가 되었길 바라오 🤍<br><br>#NOMAD #노매드<br>#CallMeBack #NOMAD_CallMeBack"
  },
  "241229": {
    "text": "노매드의 노빠꾸(NO BACK GO) EP.poster<br><br>노매드의 일상 속 행복을 찾아라❗<br>이번엔 힐링매드로 찾아온 노매드<br><br>2024.12.30 EP.07<br>NOMAD OFFICIAL 유튜브 채널에서 만나보세요! 👀<br><br>#NOMAD #노매드<br>#노매드의_노빠꾸 #NOMAD_NOBACKGO"
  },
  "250108": {
    "text": "[📷] 원데이클래스에서 만난 다도매드<br><br>#도의  #상하 #리버 가 함께한 첫 다도클래스 🍵<br>따뜻한 차와 다식이 있으면 올 겨울 이겨낼 수 있어.😌<br><br>#NOMAD #노매드 <br>#DOY #SANGHA #RIVR"
  },
  "250116": {
    "text": "[📢] NOMAD 1ST FAN CONCERT <CARNIVAL> 진행 안내<br><br>🗓 2025.02.08. SAT 7PM (KST)<br><br>🎆 SHOWKING K-POP CENTER<br>🎫 b.stage+<br><br>➫ https://nomadofficial.kr/community/board/65c1c8d06a758c09850c7003/post/6788df9f01005f140ccec056<br><br>#NOMAD #노매드<br>#CARNIVAL #카니발"
  },
  "250122": {
    "text": "NOMAD 1ST FAN CONCERT <CARNIVAL> POSTER<br>#도의 #DOY <br><br>🗓 2025.02.08. SAT 7PM (KST)<br><br>🎆 SHOWKING K-POP CENTER<br>🎫 b.stage+<br><br>➫ https://nomadofficial.kr/community/board/65c1c8d06a758c09850c7003/post/6788df9f01005f140ccec056<br><br>#NOMAD #노매드<br>#CARNIVAL #카니발"
  },
  "250125": {
    "text": "노매드의 노빠꾸(NO BACK GO) EP.poster<br><br>2025년 빠꾸 없는 노매드家 의 설날맞이‼️<br>설날매드와 함께해요.<br><br>2024.01.29 EP.08<br>NOMAD OFFICIAL 유튜브 채널에서 만나보세요! 👀<br><br>#NOMAD #노매드<br>#노매드의_노빠꾸 #NOMAD_NOBACKGO"
  },
  "250127": {
    "text": "[📷] NOMAD LIGHT STICK.pic<br><br>BASE와 함께할 CARNIVAL을<br>기다리며..💖<br><br>#NOMAD #노매드 <br>#CARNIVAL #카니발"
  },
  "250201": {
    "text": ""
  },
  "250202": {
    "text": "노매드의 <CARNIVAL>에 탑승하시겠습니까? 🤩<br><br>[팬콘 드레스코드]<br>뛰어노느라 더울테니까 반팔👕<br>-7도를 이겨낼 두꺼운 아우터는 필수🧣<br>움직이기 편한 바지 👖<br><br>놀 준비됐나요?😍<br>2월 8일 토요일에 만나요👋<br><br>#NOMAD #노매드<br>#CARNIVAL #카니발"
  },
  "250208": {
    "1": {
      "text": "노매드의 CARNIVAL에 오신 것을 환영합니다🤗 냠냠매드 베이스 사랑이 배불러 🖤<br><br>#NOMAD #노매드"
    },
    "2": {
      "text": "BASE는 NOMAD의 CARNIVAL🤍<br><br>첫 번째 팬콘 함께 즐겨줘서 너무 고마워요!<br>조만간 또 만나요👋<br><br>#NOMAD #노매드<br>#CARNIVAL #카니발"
    }
  },
  "250209": {
    "1": {
      "text": "2025 F/W SeoulFashionWeek<br>: (Corp.) Gravity , Urban Savvy<br><br>#NOMAD #노매드<br>#2025SFW #Seoulfashionweek"
    },
    "2": {
      "text": "2025 F/W SeoulFashionWeek<br>: (Corp.) Gravity , Urban Savvy<br><br>#NOMAD #노매드<br>#2025SFW #Seoulfashionweek"
    }
  },
  "250216": {
    "text": "Nonsan Strawberry Festival<br>in Jakarta 🍓<br><br>Terima kasih telah bersama kami<br>함께해주셔서 감사합니다👋<br>내일은 팬사인회에서 만나요‼️<br><br>#NOMAD #노매드"
  },
  "250228": {
    "1": {
      "text": "<𝑁𝑂𝑀𝐴𝐷 𝐷𝐸𝐵𝑈𝑇 1𝑠𝑡 𝐴𝑛𝑛𝑖𝑣𝑒𝑟𝑠𝑎𝑟𝑦><br><br>오늘 밤 유튜브 라이브 방송에서 만나요 😊🖤<br><br>#NOMAD #노매드<br>#NOMAD1stBASEcamp #NOMAD_1st_Anniversary"
    },
    "2": {
      "text": "𝑁𝑂𝑀𝐴𝐷 𝐷𝐸𝐵𝑈𝑇 1𝑠𝑡 𝐴𝑛𝑛𝑖𝑣𝑒𝑟𝑠𝑎𝑟𝑦 🎈<br><br>#NOMAD #노매드<br>#NOMAD1stBASEcamp #NOMAD_1st_Anniversary"
    },
    "3": {
      "text": "[🔴] NOMAD 1st Anniversary YOUTUBE LIVE<br><br>잠시 후 9시 40분에 만나요👋<br><br>➫ https://youtube.com/live/rIhTVVRHQ6Q?si=GZ6-6EdP5YWraG99<br><br>#NOMAD #노매드<br>#NOMAD1stBASEcamp #NOMAD_1st_Anniversary"
    }
  },
  "250301": {
    "1": {
      "text": "𝑁𝑂𝑀𝐴𝐷 𝐷𝐸𝐵𝑈𝑇 1𝑠𝑡 𝐴𝑛𝑛𝑖𝑣𝑒𝑟𝑠𝑎𝑟𝑦<br>베이스와 하루종일 함께한 알찬 1주년 ‼️<br>항상 옆에 있어줘서 고마워요 😊🖤<br><br>#NOMAD #노매드<br>#NOMAD1stBASEcamp #NOMAD_1st_Anniversary"
    },
    "2": {
      "text": "NOMAD 4cut 📸<br><br>#NOMAD #노매드<br>#NOMAD1stBASEcamp #NOMAD_1st_Anniversary"
    }
  },
  "250302": {
    "1": {
      "text": "[📞]<br>노매드에게 제일 화려했던<br>밤 하늘 불꽃처럼 베이스는 노매드의 C͙⃰A͙⃰R͙⃰N͙⃰I͙⃰V͙⃰A͙⃰L͙⃰..🎆<br><br>#NOMAD #노매드<br>#CallMeBack #NOMAD_CallMeBack"
    },
    "2": {
      "text": "[📞]<br>마지막의 마지막까지 행복했던 콜미백 🥹<br>잘가~(가지마) 행복해~(떠나지마)<br>언제나 그리워지면 언제든 𝓒𝓪𝓵𝓵 𝓜𝓮 𝓑𝓪𝓬𝓴,,🤙<br><br>#NOMAD #노매드<br>#CallMeBack #NOMAD_CallMeBack"
    }
  },
  "250305": {
    "text": "[#NOMAD] <br>僕たちは日本公演に向けて最後の練習中！！<br>期待してください〜<br>ベイス待っててね！😏😏😏<br><br>#NOMAD #노매드<br>#ノーマッド"
  },
  "250308": {
    "1": {
      "text": "[📞]<br>첫 도쿄 Call Me Back 릴리즈 이벤트 완료<br>少し後で公演で会いましょう 👋 <br><br>#NOMAD #노매드<br>#CallMeBack #NOMAD_CallMeBack"
    },
    "2": {
      "text": "[📞]<br>비가와도 눈이와도 콜미백은 계속된다 🤙<br>도쿄에서의 즐거운 추억 적립 완료🖤<br><br>#NOMAD #노매드<br>#CallMeBack #NOMAD_CallMeBack"
    }
  },
  "250309": {
    "text": "来日中のNOMADからメッセージが届きました！<br>NOMADは3月16日まで、都内各所（渋谷・豊洲・お台場など）で公演＆リリースイベント開催中！<br><br>「16日まで日本で活動中です！たくさん会いにきてくださーい！」<br><br>#NOMAD"
  },
  "250310": {
    "1": {
      "text": "[📞]<br>좋은 날씨와 베이스가 만나니 행복이 228배😌<br>늦은 시간까지 함께해줘서 고마워요<br>明日はリリースイベントで豊洲で会いましょう🖤<br><br>#NOMAD #노매드"
    },
    "2": {
      "text": "2部の7時豊洲で会いましょう<br>待ってるよ👋<br><br>#NOMAD #노매드<br>#ノーマッド"
    },
    "3": {
      "text": "[📞]<br>첫 야외 예쁜 베이스와 예쁜 도요스와 함께한 릴리즈 이벤트 🍃 <br>오늘 하루도 고생한 베이스 모두 수고했어요 <br>明日は渋谷で会いましょう👋😌 <br><br>#NOMAD #노매드<br>#CallMeBack #NOMAD_CallMeBack"
    }
  },
  "250311": {
    "1": {
      "text": "2部にいらっしゃる方,<br>雨が降るので気を付けて来てください☔️ <br><br>#NOMAD #노매드<br>#ノーマッド"
    },
    "2": {
      "text": "[📞]<br>오늘도 시부야에서 베이스들과 즐거운 하루 보낸 행복매드🥰<br>明日は横浜で待っています🤙 <br><br>#NOMAD #노매드<br>#CallMeBack #NOMAD_CallMeBack"
    }
  },
  "250312": {
    "text": "[📞]<br>요코하마를 마지막으로 릴리즈 이벤트 종료😢<br>비가오는데도 찾아와주신 베이스, 릴리즈 이벤트를 멀리서 응원해준 베이스 모두 고마워요🖤 <br>僕たちはお台場公演で会いましょう👋<br><br>#NOMAD #노매드<br>#CallMeBack #NOMAD_CallMeBack"
  },
  "250314": {
    "text": "[📞]<br>오다이바에서 첫 공연 완료🧡<br>소중한 금요일 함께해줘서 고마워요 <br>残りの週末も一緒にしましょう🤙<br><br>#NOMAD #노매드<br>#CallMeBack #NOMAD_CallMeBack"
  },
  "250315": {
    "text": "[📞]<br>마지막으로 향해가는 LIVE IN TOKYO 🎤<br>오늘도 노매드와 베이스 수고많았어요.(よしよしして☺️)<br>🫳🫳🫳🫳🫳<br>かけなおして(ToT) 📞<br><br>#NOMAD #노매드<br>#CallMeBack #NOMAD_CallMeBack"
  },
  "250316": {
    "text": "[📞]<br>NOMAD LIVE IN TOKYO 종료 😢<br>끝까지 함께 달려준 우리 베이스들, 멀리서 지켜봐준 베이스들 덕분에 소중한 시간이었습니다!! 일본에서의 마지막 공연이지만 또 다른 시작이 있으니까 앞으로의 노매드도 따라와주실거죠? 🤙<br>みんなおつかれ様でした🖤<br><br>#NOMAD #노매드<br>#CallMeBack #NOMAD_CallMeBack"
  },
  "250401": {
    "1": {
      "text": "이건 뭐임? <br><br>#NOMAD #노매드 #AprilFoolsDay"
    },
    "2": {
      "text": "예? <br><br>#NOMAD #노매드 #AprilFoolsDay"
    },
    "3": {
      "text": "Igloo 🕶️<br><br>#NOMAD #노매드 #AprilFoolsDay"
    },
    "4": {
      "text": "뽀삐뽀삐뽀 이것 뭐에요?<br><br>#NOMAD #노매드 #AprilFoolsDay"
    },
    "5": {
      "text": "상하 갤러리 털기 쉽죠? ㅋㅋ<br><br>#NOMAD #노매드 #AprilFoolsDay"
    },
    "6": {
      "text": "만우절 재밌었다ㅎㅎ<br>2023년 만우절도 기대해줘~<br><br>#NOMAD #노매드 #AprilFoolsDay"
    }
  },
  "250404": {
    "text": "노매드의 노빠꾸(NO BACK GO) EP.poster<br><br>🗣️\"그게 뭔데 리버야..?\"<br>아무도 궁금하지 않았던 리버의 오타쿠 투어,<br>어디서도 보지 못한 노매드의 노빠꾸 모먼트 대공개!<br><br>2025.04.11 EP.09<br>NOMAD OFFICIAL 유튜브 채널에서 만나보세요! 👀<br><br>#NOMAD #노매드<br>#노매드의_노빠꾸 #NOMAD_NOBACKGO"
  },
  "250412": {
    "text": "노매드의 노빠꾸 정신으로<br>닌자가 된 노매드 忍❗️🥷<br>즐거웠던 그.뭔.립 투어 ✈️  <br><br>#NOMAD #노매드 <br>#NOMAD_NOBACKGO #노매드의_노빠꾸"
  },
  "250420": {
    "text": "🦉 𝐓𝐇𝐀𝐍𝐊𝐒. 𝐁𝐀𝐒𝐄 🦉<br><br>#NOMAD #노매드 <br>#ONE #원<br>#HAPPY_ONE_DAY #HBD_ONE"
  },
  "250501": {
    "text": "NOMAD IS HERE in #한강 🎵<br>D-2‼️<br><br>📍 2025.05.03 SAT 15:00 ~ <br>📍 반포 한강공원 (달빛광장 수변무대)<br><br>#NOMAD #노매드"
  },
  "250503": {
    "text": "[📞]<br>𝗡𝗢𝗠𝗔𝗗 𝗜𝗦 𝗛𝗘𝗥𝗘 𝗶𝗻 #한강<br>반포 한강공원에서 BUSKING 완료🎵<br><br>추웠던 날씨에 뜨거웠던 버스킹<br>같이 즐겨주셔서 감사합니다🖤<br><br>#NOMAD #노매드<br>#NOMAD_IS_HERE_in_HangangRiver"
  },
  "250505": {
    "text": "NOMAD Children’s Day ▶ #초딩매드 ◀<br><br>#NOMAD #노매드<br>#DOY #도의"
  },
  "250531": {
    "text": "[📞]<br>오랜만에 베이스들과 함께한 영상통화 이벤트 :)<br>期待在上海與大家见面的那一天!<br>행복한 주말 보내요😉<br><br>#NOMAD #노매드<br>#CallMeBack #NOMAD_CallMeBack"
  },
  "250607": {
    "text": "[📞]<br>오랜만에 베이스와 함께한 상하이 로맨스 💗<br>비가 오는 상하이에서의 토요일, 함께해 줘서 고마워요<br>下雨天最适合想你 💭<br><br>#NOMAD #노매드<br>#CallMeBack #NOMAD_CallMeBack"
  },
  "250608": {
    "text": "[#도의]<br>✈️<br><br>#NOMAD #노매드 <br>#DOY #도의"
  },
  "250612": {
    "text": "NOMAD X 撕拉片 📸<br><br>#NOMAD #노매드 <br>#撕拉片 #티어오프"
  },
  "250613": {
    "text": "2025 부산원아시아페스티벌 쇼케이스 🔥<br>뜨겁게 함께해 주셔서 진심으로 감사합니다!<br>오늘의 열기, 오래오래 잊지 못할 거예요☺️<br><br>#NOMAD #노매드"
  },
  "250702": {
    "text": "7월에 찾아온 #도_쏜_트 🗒️<br><br>❰오늘의 메뉴 : 뽈살❱<br>▶️ EP.00 맛집노트 소개서 보기<br>https://youtu.be/7xDmSk2b2UQ<br><br>도의의 맛집노트는 계속된다🤤‼️<br><br>#NOMAD #노매드"
  },
  "250713": {
    "text": "나이스데이에 나이스한 베이스와의 만남<br>남은 하루도 나이스하게 보내기 😉🖤<br><br>#NOMAD #노매드"
  },
  "250719": {
    "text": "Namaste India 🇮🇳<br>All India K-POP Contest 2025에서 만나요☺️<br><br>#NOMAD #노매드"
  },
  "250720": {
    "text": "All India K-POP Contest 2025 🇮🇳<br>뜨거운 에너지 감사합니다❤️‍🔥<br>दोबारा जल्दी मिलेंगे 🤙<br><br>#NOMAD #노매드"
  },
  "250808": {
    "text": "NOMAD is QINGDAO❗️<br>노매드가 칭다오에 왔다오☺️ <br>오늘 하루도 베이스 고생많았다오. 즐거운 금요일 보내다오🖤 <br><br>#NOMAD #노매드"
  },
  "250809": {
    "text": "칭다오에서 보낸 멋진 이틀<br>좋은 추억 만들었다오😊<br>베이스도 남은 주말 행복하게 보내기💭 <br><br>#NOMAD #노매드"
  },
  "250916": {
    "text": ""
  },
  "250927": {
    "text": "패션한국 vol.9 ‘노매드(Nomad)’ 티저, 자유와 도전의 메시지 담다<br><br>🔗 https://sports.hankooki.com/news/articleView.html?idxno=6911287<br><br>#NOMAD #노매드<br><br>𝐇𝐀𝐏𝐏𝐘 𝐃𝐎𝐘 𝐃𝐀𝐘 😎<br><br>#NOMAD #노매드 <br>#DOY #도의<br>#HAPPY_DOY_DAY #HBD_DOY"
  },
  "250928": {
    "text": "2025 http://C.AT WORK FESTA | ERER <br><br>#NOMAD #노매드<br>#캣워크페스타 #CatWorkFesta"
  },
  "251001": {
    "text": "패션한국 vol.9 커버스토리 DAY 1, 노매드(NOMAD) 다섯 멤버가 전하는 희망<br><br>🔗 https://sports.hankooki.com/news/articleView.html?idxno=6911765<br><br>#NOMAD #노매드"
  },
  "251004": {
    "text": "패션한국 Vol.9 Cover Story DAY 2 — 다섯 개의 시선, 하나의 호흡<br><br>🔗 https://sports.hankooki.com/news/articleView.html?idxno=6911997 <br><br>#NOMAD #노매드"
  },
  "251005": {
    "text": "패션한국 Vol.9 Cover Story DAY 3 — 다섯 개의 초상, 하나의 이야기<br><br>🔗 https://sports.hankooki.com/news/articleView.html?idxno=6912048<br><br>#NOMAD #노매드"
  },
  "251008": {
    "text": "Fashion Hankook : Oct Vol.9 📸<br><br>#NOMAD #노매드"
  },
  "251018": {
    "text": "오랜만에 만난 NOMAD 🖤 BASE<br>소중한 주말 함께해 줘서 고마워요 ☺️<br>[🎧 오노추 : NOMAD - Oasis] <br><br>#NOMAD #노매드"
  },
  "251024": {
    "text": "NUYH NEWYORK 26 S/S Collection <br>《SHA:DOW | 영影》<br><br>#NOMAD #노매드"
  },
  "251027": {
    "text": "가을에 찾아온 NOMAD in Hangzhou 🍂<br>함께 만들어준 항저우의 추억, 고마워요🤎<br><br>#NOMAD #노매드"
  },
  "251109": {
    "text": ""
  },
  "251120": {
    "text": "NOMAD <NO PLAN><br>🔔 D-1 🔔<br><br>🗓 2025.11.21 FRI 19:00(KST)<br>📍 SEONGAM ART HALL<br>🎫 Million Music : http://millionmusic.co.kr <br><br>#NOMAD #노매드<br>#NO_PLAN #노플랜<br><br>[#상하]<br>1년 반이라는 시간 동안 일요일을 함께해 주셔서 고맙습니다!<br>많은 걸 배우고 느낀 시간이었습니다😌<br>마지막까지 OBS 인사이드 스토리에서 함께해요!🤍<br><br>#NOMAD #노매드<br>#SANGHA #상하"
  },
  "251122": {
    "1": {
      "text": "#NO_PLAN <br>베이스라는 이유로 완성된 노매드의 PLAN 🖤<br>멀리서, 또 가까이에서 함께해 준 모든 BASE 감사합니다. <br><br>#NOMAD #노매드"
    },
    "2": {
      "text": "𝐵𝑎𝑐𝑘 𝑇𝑜 𝐵𝐴𝑆𝐸 💐<br>기억 속에 오래도록 피어날 하루☺️🩷<br>함께해 주셔서 감사합니다. 좋은 주말 보내기! <br><br>#NOMAD #노매드"
    }
  },
  "251125": {
    "text": "𝐵𝑎𝑐𝑘 𝑇𝑜 𝐵𝐴𝑆𝐸 💐<br><br>#NOMAD #노매드"
  }
}